trading_api_wrappers/__init__.py
trading_api_wrappers/_version.py
trading_api_wrappers/auth.py
trading_api_wrappers/base.py
trading_api_wrappers/bitcoinity/__init__.py
trading_api_wrappers/bitcoinity/client.py
trading_api_wrappers/bitex/__init__.py
trading_api_wrappers/bitex/client_public.py
trading_api_wrappers/bitex/models.py
trading_api_wrappers/bitfinex/__init__.py
trading_api_wrappers/bitfinex/client_auth_v1.py
trading_api_wrappers/bitfinex/client_public_v1.py
trading_api_wrappers/bitfinex/client_public_v2.py
trading_api_wrappers/bitfinex/constants_v1.py
trading_api_wrappers/bitfinex/constants_v2.py
trading_api_wrappers/bitfinex/models_v2.py
trading_api_wrappers/bitstamp/__init__.py
trading_api_wrappers/bitstamp/client_auth.py
trading_api_wrappers/bitstamp/client_public.py
trading_api_wrappers/bitstamp/constants.py
trading_api_wrappers/buda/__init__.py
trading_api_wrappers/buda/client_auth.py
trading_api_wrappers/buda/client_public.py
trading_api_wrappers/buda/constants.py
trading_api_wrappers/buda/models.py
trading_api_wrappers/coindesk/__init__.py
trading_api_wrappers/coindesk/client.py
trading_api_wrappers/coinmarketcap/__init__.py
trading_api_wrappers/coinmarketcap/client.py
trading_api_wrappers/common.py
trading_api_wrappers/cryptomkt/__init__.py
trading_api_wrappers/cryptomkt/client_auth.py
trading_api_wrappers/cryptomkt/client_public.py
trading_api_wrappers/cryptomkt/constants.py
trading_api_wrappers/cryptomkt/models.py
trading_api_wrappers/currencylayer/__init__.py
trading_api_wrappers/currencylayer/client.py
trading_api_wrappers/errors.py
trading_api_wrappers/kraken/__init__.py
trading_api_wrappers/kraken/client_auth.py
trading_api_wrappers/kraken/client_public.py
trading_api_wrappers/kraken/constants.py
trading_api_wrappers/oxr/__init__.py
trading_api_wrappers/oxr/client.py
trading_api_wrappers/ripio/__init__.py
trading_api_wrappers/ripio/clients.py
trading_api_wrappers/ripio/models.py
trading_api_wrappers/sfox/__init__.py
trading_api_wrappers-0.18.1.dist-info/LICENSE
trading_api_wrappers-0.18.1.dist-info/WHEEL
trading_api_wrappers-0.18.1.dist-info/METADATA
trading_api_wrappers-0.18.1.dist-info/RECORD
