Metadata-Version: 2.1
Name: trading-api-wrappers
Version: 0.18.1
Summary: Clients for popular Crypto Exchanges and other useful services
Home-page: https://github.com/snake575/trading-bots
License: MIT
Author: Felipe Aranguiz
Author-email: faranguiz575@gmail.com
Requires-Python: >=3.6.2,<4.0.0
Classifier: Development Status :: 4 - Beta
Classifier: Intended Audience :: Developers
Classifier: License :: OSI Approved :: MIT License
Classifier: Natural Language :: English
Classifier: Operating System :: OS Independent
Classifier: Programming Language :: Python
Classifier: Programming Language :: Python :: 3
Classifier: Programming Language :: Python :: 3.6
Classifier: Programming Language :: Python :: 3.7
Classifier: Programming Language :: Python :: 3.8
Classifier: Programming Language :: Python :: 3.9
Classifier: Programming Language :: Python :: Implementation :: CPython
Classifier: Programming Language :: Python :: Implementation :: PyPy
Requires-Dist: backoff (>=1.11.1,<2.0.0)
Requires-Dist: importlib-metadata (>=4.6.4,<5.0.0); python_version < "3.8"
Requires-Dist: requests (>=2.26.0,<3.0.0)
Requires-Dist: requests-toolbelt (>=0.9.1,<0.10.0)
Project-URL: Repository, https://github.com/delta575/trading-bots
